{
	"response": [
		{
			"maintainer": "johnmart19",
			"oem": "Poco",
			"device": "Redmi K40/ POCO F3/ Mi 11x",
			"filename": "VoidUI-Thunderstorm-alioth-13.0-20230628-1414-OFFICIAL.zip",
			"download": "https://bruhmoment.co/0:/Other/VoidUI-Thunderstorm-alioth-13.0-20230628-1414-OFFICIAL.zip",
			"timestamp": 1687961598,
			"md5": "c1a145bd7563c292bb6490f2eec749e1",
			"sha256": "c176b58d7e821f57e535a9fa1c0ce563fdd0e00cd697e96d3c08db7353d486ee",
			"size": 2146492207,
			"version": Thunderstorm,
			"buildtype": "Daily / Weekly Builds",
			"forum": "https://t.me/VoidUI",
			"firmware": "https://xiaomifirmwareupdater.com/firmware/alioth/",
			"modem": "",
			"bootloader": "",
			"recovery": "https://eu.dl.twrp.me/alioth/",
			"paypal": "https://www.patreon.com/johnmart19",
			"telegram": "https://t.me/VoidUI_Updates/",
			"dt": "https://github.com/VoidUI-Devices/device_xiaomi_alioth",
			"common-dt": "https://github.com/VoidUI-Devices/device_xiaomi_sm8250-common",
			"kernel": "https://github.com/VoidUI-Devices/kernel_xiaomi_sm8250"
		}
	]
}
