{
	"response": [
		{
			"maintainer": "johnmart19",
			"oem": "Poco",
			"device": "Redmi K40/ POCO F3/ Mi 11x",
			"filename": "VoidUI-Tiramisu-alioth-13.0-20221004-0650-OFFICIAL.zip",
			"download": "https://void.siddrive.ga/0:/VoidUI-Tiramisu-alioth-13.0-20221004-0650-OFFICIAL.zip",
			"timestamp": 1664865741,
			"md5": "58cee9c2b501524b1c91a5f84dba9f17",
			"sha256": "19583ae886288003f06519312e70eed9fec10c4315afde1ca9ad03797f0d8f6f",
			"size": 1799878417,
			"version": Tiramisu,
			"buildtype": "Android 13 Early Development",
			"forum": "https://t.me/VoidUI",
			"firmware": "https://xiaomifirmwareupdater.com/firmware/alioth/",
			"modem": "",
			"bootloader": "",
			"recovery": "https://eu.dl.twrp.me/alioth/",
			"paypal": "https://www.patreon.com/johnmart19",
			"telegram": "https://t.me/voidui_alioth",
			"dt": "https://github.com/VoidUI-Devices/device_xiaomi_alioth",
			"common-dt": "https://github.com/VoidUI-Devices/device_xiaomi_sm8250-common",
			"kernel": "https://github.com/VoidUI-Devices/kernel_xiaomi_sm8250"
		}
	]
}
